__init__.py
jeremydimond_pygamesim-1.1.8.dist-info/licenses/LICENSE
pygamesim/__init__.py
pygamesim/simulator.py
pygamesim/cardgames/__init__.py
pygamesim/cardgames/cards.py
pygamesim/cardgames/blackjack/__init__.py
pygamesim/cardgames/blackjack/hand.py
pygamesim/cardgames/blackjack/casino/__init__.py
pygamesim/cardgames/blackjack/casino/dealer.py
pygamesim/cardgames/blackjack/casino/game.py
pygamesim/cardgames/blackjack/casino/player.py
pygamesim/cardgames/blackjack/casino/watchers.py
pygamesim/cardgames/blackjack/casino/strategy/__init__.py
pygamesim/cardgames/blackjack/casino/strategy/basic.py
pygamesim/cardgames/blackjack/casino/strategy/counting.py
pygamesim/cardgames/blackjack/casino/strategy/scenario.py
jeremydimond_pygamesim-1.1.8.dist-info/METADATA
jeremydimond_pygamesim-1.1.8.dist-info/WHEEL
jeremydimond_pygamesim-1.1.8.dist-info/top_level.txt
jeremydimond_pygamesim-1.1.8.dist-info/RECORD
