Metadata-Version: 2.4
Name: jeremydimond.pygamesim
Version: 1.1.8
Summary: Python game simulator.
Author-email: Jeremy Dimond <jeremy@jeremydimond.com>
License: Copyright © 2019-2026 Jeremy Dimond
Project-URL: Homepage, https://github.com/jeremydimond/pygamesim
Keywords: jeremydimond,game,simulator,simulation,blackjack
Classifier: License :: OSI Approved :: MIT License
Classifier: Programming Language :: Python
Classifier: Programming Language :: Python :: 3
Requires-Python: >=3.9
License-File: LICENSE
Provides-Extra: dev
Requires-Dist: jeremydimond.pytesthelpers==1.0.4; extra == "dev"
Requires-Dist: pytest<9.0.0; extra == "dev"
Requires-Dist: pytest-cov; extra == "dev"
Requires-Dist: pytest-tldr; extra == "dev"
Requires-Dist: bumpver; extra == "dev"
Requires-Dist: build; extra == "dev"
Requires-Dist: twine; extra == "dev"
Dynamic: license-file
